dimini/__init__.py
dimini/dependency.py
dimini/di.py
dimini/exceptions.py
dimini/integrations.py
dimini/scopes.py
dimini-1.0.0.dist-info/LICENSE
dimini-1.0.0.dist-info/METADATA
dimini-1.0.0.dist-info/WHEEL
dimini-1.0.0.dist-info/top_level.txt
dimini-1.0.0.dist-info/RECORD
