Metadata-Version: 2.1
Name: dimini
Version: 1.0.0
Summary: Minimalistic Dependency Injection for Python
Author-email: Anton Miasnikov <anton2008m@gmail.com>
License: MIT License
Classifier: Development Status :: 5 - Production/Stable
Classifier: Programming Language :: Python
Classifier: Programming Language :: Python :: Implementation :: CPython
Classifier: Programming Language :: Python :: 3
Classifier: Programming Language :: Python :: 3 :: Only
Classifier: Programming Language :: Python :: 3.9
Classifier: Programming Language :: Python :: 3.10
Classifier: Programming Language :: Python :: 3.11
Classifier: Programming Language :: Python :: 3.12
Classifier: Intended Audience :: Developers
Classifier: License :: OSI Approved :: MIT License
Classifier: Operating System :: OS Independent
Classifier: Topic :: Software Development
Requires-Python: >=3.9
License-File: LICENSE
Provides-Extra: dev
Requires-Dist: pre-commit <4.0.0 ; extra == 'dev'
Requires-Dist: pytest <9.0.0 ; extra == 'dev'
Requires-Dist: pytest-asyncio <1.0.0 ; extra == 'dev'
Requires-Dist: pytest-cov[all] <6.0.0 ; extra == 'dev'
Requires-Dist: ruff <1.0.0 ; extra == 'dev'
